toscana/__init__.py
toscana/data_post_processing/__init__.py
toscana/data_post_processing/_post_processing.py
toscana/data_pre_processing/__init__.py
toscana/data_pre_processing/grid_creation.py
toscana/data_pre_processing/meteorological_files.py
toscana/data_pre_processing/raster_preprocessing.py
toscana/data_pre_processing/shp_preprocessing.py
toscana/results/__init__.py
toscana/results/results_vizualisation.py
toscana/results/village_characteristics.py
toscana/solar_simulation/__init__.py
toscana/solar_simulation/_sebe_simulation.py
toscana/utils/__init__.py
toscana/utils/_utils.py
toscana-0.2.3.dist-info/licenses/LICENSE
toscana-0.2.3.dist-info/METADATA
toscana-0.2.3.dist-info/WHEEL
toscana-0.2.3.dist-info/top_level.txt
toscana-0.2.3.dist-info/RECORD
