Metadata-Version: 2.4
Name: toscana
Version: 0.2.3
Summary: toscana allows to run SEBE simulation at village scale to obtain building rooftop irradiation, using open-access database (BDTOPO, OpenDEM)
Author-email: Apolline Ferry <apolline.ferry@laposte.net>
License-Expression: Apache-2.0
Project-URL: Laboratory, https://www.univ-smb.fr/locie/
Project-URL: Repository, https://github.com/locie/toscana
Project-URL: Documentation, https://github.com/locie/toscana/blob/main/doc/_build/toscana.pdf
Keywords: irradiation,solar,cadastre,gis,rooftop
Classifier: Intended Audience :: Science/Research
Classifier: Natural Language :: English
Classifier: Programming Language :: Python :: 3.9
Classifier: Programming Language :: Python :: 3.10
Classifier: Topic :: Scientific/Engineering :: Information Analysis
Classifier: Topic :: Scientific/Engineering :: Physics
Classifier: Topic :: Scientific/Engineering :: Visualization
Requires-Python: >=3.9
License-File: LICENSE
Dynamic: license-file
